LICENSE
README.md
setup.cfg
setup.py
okta_awscli.egg-info/PKG-INFO
okta_awscli.egg-info/SOURCES.txt
okta_awscli.egg-info/dependency_links.txt
okta_awscli.egg-info/entry_points.txt
okta_awscli.egg-info/requires.txt
okta_awscli.egg-info/top_level.txt
oktaawscli/__init__.py
oktaawscli/aws_auth.py
oktaawscli/okta_auth.py
oktaawscli/okta_auth_config.py
oktaawscli/okta_auth_mfa_app.py
oktaawscli/okta_auth_mfa_base.py
oktaawscli/okta_awscli.py
oktaawscli/version.py